{
  "objectInfo" : {
    "id" : "hPJjmiUmdg5icL1uL5mYeZ",
    "name" : "MT-NetSuite",
    "type" : "MTT",
    "metadata" : {
      "modelVersion" : {
        "major" : 0,
        "minor" : 0
      },
      "repoInfo" : {
        "repoHandle" : "012CQZ0Z0000000001CF"
      },
      "contextAttributes" : [ {
        "name" : "id",
        "value" : "@1"
      } ],
      "additionalInfo" : {
        "description" : "",
        "contentType" : null,
        "documentState" : "VALID"
      }
    }
  },
  "dataFileExtension" : "zip",
  "updateTime" : "2024-04-08T15:52:03.076Z",
  "objectRefs" : [ {
    "id" : "a2LkuAtZA1DhUu4JEHCdSr",
    "name" : "Mapping39",
    "type" : "DTEMPLATE",
    "metadata" : {
      "modelVersion" : {
        "major" : 0,
        "minor" : 0
      },
      "repoInfo" : {
        "repoHandle" : "012CQZ170000000001F2"
      },
      "contextAttributes" : [ {
        "name" : "id",
        "value" : "@1"
      } ],
      "additionalInfo" : {
        "description" : "",
        "contentType" : null,
        "documentState" : "VALID"
      }
    },
    "path" : "/Explore/User-Jayesh/Concur-NS"
  }, {
    "id" : "8KnOnFd66delMaTtLAyqiv",
    "name" : "NetSuite Sandbox",
    "type" : "Connection",
    "metadata" : {
      "modelVersion" : {
        "major" : 0,
        "minor" : 0
      },
      "repoInfo" : {
        "repoHandle" : "012CQZ0B000000000039"
      },
      "contextAttributes" : null,
      "additionalInfo" : {
        "description" : null,
        "contentType" : "JSON",
        "documentState" : "COMPLETE"
      }
    },
    "path" : "/SYS"
  }, {
    "id" : "5mQgwCDK52Pef0vB3dqr2j",
    "name" : "FileShared_Concur",
    "type" : "Connection",
    "metadata" : {
      "modelVersion" : {
        "major" : 0,
        "minor" : 0
      },
      "repoInfo" : {
        "repoHandle" : "012CQZ0B000000000037"
      },
      "contextAttributes" : null,
      "additionalInfo" : {
        "description" : null,
        "contentType" : "JSON",
        "documentState" : "COMPLETE"
      }
    },
    "path" : "/SYS"
  }, {
    "id" : "0IOccxVZUCdgmeZRWyjmQW",
    "name" : "SA-Group1-UAT",
    "type" : "AgentGroup",
    "metadata" : {
      "modelVersion" : {
        "major" : 0,
        "minor" : 0
      },
      "repoInfo" : {
        "repoHandle" : "012CQZ25000000000003"
      },
      "contextAttributes" : null,
      "additionalInfo" : {
        "description" : null,
        "contentType" : "JSON",
        "documentState" : "VALID"
      }
    },
    "path" : "/SYS"
  } ]
}